Workbook
Name sales_data: Table2[]
Name Slicer_Quarter: #N/A
Name Slicer_Region: #N/A

Sheet YOUR_TASKS_README
A1: 📋 AL-RIYAN TRADING CO. — Excel Portfolio Project | Task Instructions for Riyan
A3: PROJECT OVERVIEW
A4: Company: AL-RIYAN TRADING CO. (Fictional KSA business — perfect for your GCC portfolio)
A5: Data Period: FY 2023–24 (April 2023 to March 2024)
A6: Sheets: RAW_Sales_Data | Monthly_Targets | Expenses_Data | Dashboard (you build this)
A7: Final Goal: A fully interactive Excel Dashboard with KPIs, Charts, Slicers, and Summary
A9: PHASE 1 — DATA CLEANING & PREP (Sheet: RAW_Sales_Data)
A10: TASK 1.1 → Freeze top 2 rows (already done). Explore all 12 columns. Understand the data.
A11: TASK 1.2 → Add column M: 'Profit_SAR' = Total_Revenue_SAR - Cost_SAR (formula, not hardcode)
A12: TASK 1.3 → Add column N: 'Profit_Margin_%' = Profit_SAR / Total_Revenue_SAR (format as %)
A13: TASK 1.4 → Add column O: 'Performance_Flag' = IF(Profit_Margin_% >= 30%, 'High','Low')
A14: TASK 1.5 → Apply conditional formatting: Green fill for High, Red fill for Low in column O
... A72: ✅ Example finding: 'Riyadh region contributed 34% of total annual revenue'

Sheet RAW_Sales_Data
A1: AL-RIYAN TRADING CO. — Monthly Sales Raw Data (FY 2023–24) | KSA Market
A2: Order_ID | B2: Date | C2: Month | D2: Quarter | E2: Salesperson | F2: Region | G2: Product_Category | H2: Product_Name | I2: Units_Sold | J2: Unit_Price_SAR | K2: Total_Revenue_SAR | L2: Cost_SAR | M2: Profit_SAR | N2: Profit_Margin% | O2: Performance_Flag
A3: ORD-1001 | B3: 45040 | C3: Apr-23 | D3: Q1 | E3: Fatima Hassan | F3: Jeddah | G3: Electronics | H3: Logitech Keyboard | I3: 5 | J3: 85 | K3: 425 | L3: 276.25 | M3: =Table2[[#This Row],[Total_Revenue_SAR]]-Table2[[#This Row],[Cost_SAR]] -> 148.75 | N3: =Table2[[#This Row],[Profit_SAR]]/Table2[[#This Row],[Total_Revenue_SAR]] -> 0.35 | O3: =IF(Table2[[#This Row],[Profit_Margin%]]>=40%,"High","Low") -> Low
A4: ORD-1002 | B4: 45018 | C4: Apr-23 | D4: Q1 | E4: Omar Siddiqui | F4: Riyadh | G4: Electronics | H4: Webcam | I4: 14 | J4: 120 | K4: 1680 | L4: 1092 | M4: =Table2[[#This Row],[Total_Revenue_SAR]]-Table2[[#This Row],[Cost_SAR]] -> 588 | N4: =Table2[[#This Row],[Profit_SAR]]/Table2[[#This Row],[Total_Revenue_SAR]] -> 0.35 | O4: =IF(Table2[[#This Row],[Profit_Margin%]]>=40%,"High","Low") -> Low
A5: ORD-1003 | B5: 45036 | C5: Apr-23 | D5: Q1 | E5: Fatima Hassan | F5: Jeddah | G5: Electronics | H5: Laptop HP | I5: 17 | J5: 450 | K5: 7650 | L5: 4972.5 | M5: =Table2[[#This Row],[Total_Revenue_SAR]]-Table2[[#This Row],[Cost_SAR]] -> 2677.5 | N5: =Table2[[#This Row],[Profit_SAR]]/Table2[[#This Row],[Total_Revenue_SAR]] -> 0.35 | O5: =IF(Table2[[#This Row],[Profit_Margin%]]>=40%,"High","Low") -> Low
A6: ORD-1004 | B6: 45039 | C6: Apr-23 | D6: Q1 | E6: Riyan K | F6: Jeddah | G6: Electronics | H6: Webcam | I6: 21 | J6: 120 | K6: 2520 | L6: 1638 | M6: =Table2[[#This Row],[Total_Revenue_SAR]]-Table2[[#This Row],[Cost_SAR]] -> 882 | N6: =Table2[[#This Row],[Profit_SAR]]/Table2[[#This Row],[Total_Revenue_SAR]] -> 0.35 | O6: =IF(Table2[[#This Row],[Profit_Margin%]]>=40%,"High","Low") -> Low
A7: ORD-1005 | B7: 45025 | C7: Apr-23 | D7: Q1 | E7: Sara Al-Otaibi | F7: Jeddah | G7: IT Equipment | H7: RAM Module | I7: 19 | J7: 175 | K7: 3325 | L7: 2061.5 | M7: =Table2[[#This Row],[Total_Revenue_SAR]]-Table2[[#This Row],[Cost_SAR]] -> 1263.5 | N7: =Table2[[#This Row],[Profit_SAR]]/Table2[[#This Row],[Total_Revenue_SAR]] -> 0.38 | O7: =IF(Table2[[#This Row],[Profit_Margin%]]>=40%,"High","Low") -> Low
A8: ORD-1006 | B8: 45021 | C8: Apr-23 | D8: Q1 | E8: Khalid Nasser | F8: Mecca | G8: Electronics | H8: Dell Monitor | I8: 9 | J8: 320 | K8: 2880 | L8: 1872 | M8: =Table2[[#This Row],[Total_Revenue_SAR]]-Table2[[#This Row],[Cost_SAR]] -> 1008 | N8: =Table2[[#This Row],[Profit_SAR]]/Table2[[#This Row],[Total_Revenue_SAR]] -> 0.35 | O8: =IF(Table2[[#This Row],[Profit_Margin%]]>=40%,"High","Low") -> Low
A9: ORD-1007 | B9: 45020 | C9: Apr-23 | D9: Q1 | E9: Ahmed Al-Ghamdi | F9: Riyadh | G9: Office Supplies | H9: Pen Box | I9: 13 | J9: 35 | K9: 455 | L9: 227.5 | M9: =Table2[[#This Row],[Total_Revenue_SAR]]-Table2[[#This Row],[Cost_SAR]] -> 227.5 | N9: =Table2[[#This Row],[Profit_SAR]]/Table2[[#This Row],[Total_Revenue_SAR]] -> 0.5 | O9: =IF(Table2[[#This Row],[Profit_Margin%]]>=40%,"High","Low") -> High
A10: ORD-1008 | B10: 45040 | C10: Apr-23 | D10: Q1 | E10: Khalid Nasser | F10: Medina | G10: Furniture | H10: Filing Cabinet | I10: 2 | J10: 290 | K10: 580 | L10: 348 | M10: =Table2[[#This Row],[Total_Revenue_SAR]]-Table2[[#This Row],[Cost_SAR]] -> 232 | N10: =Table2[[#This Row],[Profit_SAR]]/Table2[[#This Row],[Total_Revenue_SAR]] -> 0.4 | O10: =IF(Table2[[#This Row],[Profit_Margin%]]>=40%,"High","Low") -> High
A11: ORD-1009 | B11: 45034 | C11: Apr-23 | D11: Q1 | E11: Sara Al-Otaibi | F11: Riyadh | G11: Stationery | H11: Scissors | I11: 3 | J11: 19 | K11: 57 | L11: 25.65 | M11: =Table2[[#This Row],[Total_Revenue_SAR]]-Table2[[#This Row],[Cost_SAR]] -> 31.35 | N11: =Table2[[#This Row],[Profit_SAR]]/Table2[[#This Row],[Total_Revenue_SAR]] -> 0.55 | O11: =IF(Table2[[#This Row],[Profit_Margin%]]>=40%,"High","Low") -> High
A12: ORD-1010 | B12: 45039 | C12: Apr-23 | D12: Q1 | E12: Omar Siddiqui | F12: Dammam | G12: Furniture | H12: Whiteboard | I12: 7 | J12: 175 | K12: 1225 | L12: 735 | M12: =Table2[[#This Row],[Total_Revenue_SAR]]-Table2[[#This Row],[Cost_SAR]] -> 490 | N12: =Table2[[#This Row],[Profit_SAR]]/Table2[[#This Row],[Total_Revenue_SAR]] -> 0.4 | O12: =IF(Table2[[#This Row],[Profit_Margin%]]>=40%,"High","Low") -> High
A13: ORD-1011 | B13: 45019 | C13: Apr-23 | D13: Q1 | E13: Nora Bakr | F13: Jeddah | G13: Electronics | H13: Laptop HP | I13: 10 | J13: 450 | K13: 4500 | L13: 2925 | M13: =Table2[[#This Row],[Total_Revenue_SAR]]-Table2[[#This Row],[Cost_SAR]] -> 1575 | N13: =Table2[[#This Row],[Profit_SAR]]/Table2[[#This Row],[Total_Revenue_SAR]] -> 0.35 | O13: =IF(Table2[[#This Row],[Profit_Margin%]]>=40%,"High","Low") -> Low
A14: ORD-1012 | B14: 45073 | C14: May-23 | D14: Q1 | E14: Sara Al-Otaibi | F14: Dammam | G14: Electronics | H14: USB Hub | I14: 21 | J14: 45 | K14: 945 | L14: 614.25 | M14: =Table2[[#This Row],[Total_Revenue_SAR]]-Table2[[#This Row],[Cost_SAR]] -> 330.75 | N14: =Table2[[#This Row],[Profit_SAR]]/Table2[[#This Row],[Total_Revenue_SAR]] -> 0.35 | O14: =IF(Table2[[#This Row],[Profit_Margin%]]>=40%,"High","Low") -> Low
... A174: ORD-1172 | B174: 45365 | C174: Mar-24 | D174: Q4 | E174: Omar Siddiqui | F174: Riyadh | G174: Stationery | H174: Correction Tape | I174: 2 | J174: 14 | K174: 28 | L174: 12.6 | M174: =Table2[[#This Row],[Total_Revenue_SAR]]-Table2[[#This Row],[Cost_SAR]] -> 15.4 | N174: =Table2[[#This Row],[Profit_SAR]]/Table2[[#This Row],[Total_Revenue_SAR]] -> 0.55 | O174: =IF(Table2[[#This Row],[Profit_Margin%]]>=40%,"High","Low") -> High

Sheet Monthly_Targets
A1: AL-RIYAN TRADING CO. — Monthly Sales Targets vs Actual (FY 2023–24)
A2: Month | B2: Quarter | C2: Target_SAR | D2: Actual_SAR | E2: Variance_SAR | F2: MoM Growth%
A3: Apr-23 | B3: Q1 | C3: 42000 | D3: 38500 | E3: =D3-C3 -> -3500
A4: May-23 | B4: Q1 | C4: 45000 | D4: 46200 | E4: =D4-C4 -> 1200 | F4: =(D4-D3)/D3 -> 0.2
A5: Jun-23 | B5: Q1 | C5: 48000 | D5: 51000 | E5: =D5-C5 -> 3000 | F5: =(D5-D4)/D4 -> 0.1038961
A6: Jul-23 | B6: Q2 | C6: 50000 | D6: 48800 | E6: =D6-C6 -> -1200 | F6: =(D6-D5)/D5 -> -0.043137255
A7: Aug-23 | B7: Q2 | C7: 52000 | D7: 53400 | E7: =D7-C7 -> 1400 | F7: =(D7-D6)/D6 -> 0.094262295
A8: Sep-23 | B8: Q2 | C8: 55000 | D8: 58900 | E8: =D8-C8 -> 3900 | F8: =(D8-D7)/D7 -> 0.10299625
A9: Oct-23 | B9: Q3 | C9: 57000 | D9: 55000 | E9: =D9-C9 -> -2000 | F9: =(D9-D8)/D8 -> -0.066213922
A10: Nov-23 | B10: Q3 | C10: 60000 | D10: 63200 | E10: =D10-C10 -> 3200 | F10: =(D10-D9)/D9 -> 0.14909091
A11: Dec-23 | B11: Q3 | C11: 65000 | D11: 70100 | E11: =D11-C11 -> 5100 | F11: =(D11-D10)/D10 -> 0.10917722
A12: Jan-24 | B12: Q4 | C12: 58000 | D12: 54300 | E12: =D12-C12 -> -3700 | F12: =(D12-D11)/D11 -> -0.2253923
A13: Feb-24 | B13: Q4 | C13: 56000 | D13: 57800 | E13: =D13-C13 -> 1800 | F13: =(D13-D12)/D12 -> 0.064456722
A14: Mar-24 | B14: Q4 | C14: 54000 | D14: 52600 | E14: =D14-C14 -> -1400 | F14: =(D14-D13)/D13 -> -0.089965398
A15: TOTAL | C15: =SUM(C3:C14) -> 642000 | D15: =SUM(D3:D14) -> 649800 | E15: =SUM(E3:E14) -> 7800

Sheet Expenses_Data
A1: AL-RIYAN TRADING CO. — Monthly Operating Expenses (FY 2023–24)
A2: Month | B2: Quarter | C2: Salaries_SAR | D2: Rent_SAR | E2: Marketing_SAR | F2: Logistics_SAR | G2: Utilities_SAR | H2: Miscellaneous_SAR | I2: Total_Expenses_SAR
A3: Apr-23 | B3: Q1 | C3: 18000 | D3: 8500 | E3: 3200 | F3: 2800 | G3: 1100 | H3: 950 | I3: =SUM(C3:H3) -> 34550
A4: May-23 | B4: Q1 | C4: 18000 | D4: 8500 | E4: 3400 | F4: 2900 | G4: 1050 | H4: 880 | I4: =SUM(C4:H4) -> 34730
A5: Jun-23 | B5: Q1 | C5: 18500 | D5: 8500 | E5: 3600 | F5: 3100 | G5: 1200 | H5: 920 | I5: =SUM(C5:H5) -> 35820
A6: Jul-23 | B6: Q2 | C6: 19000 | D6: 8500 | E6: 4000 | F6: 3300 | G6: 1150 | H6: 1000 | I6: =SUM(C6:H6) -> 36950
A7: Aug-23 | B7: Q2 | C7: 19000 | D7: 8500 | E7: 3800 | F7: 3200 | G7: 1100 | H7: 870 | I7: =SUM(C7:H7) -> 36470
A8: Sep-23 | B8: Q2 | C8: 19000 | D8: 8500 | E8: 4200 | F8: 3500 | G8: 1250 | H8: 950 | I8: =SUM(C8:H8) -> 37400
A9: Oct-23 | B9: Q3 | C9: 19500 | D9: 8500 | E9: 4500 | F9: 3600 | G9: 1200 | H9: 1100 | I9: =SUM(C9:H9) -> 38400
A10: Nov-23 | B10: Q3 | C10: 19500 | D10: 8500 | E10: 5000 | F10: 3800 | G10: 1300 | H10: 1050 | I10: =SUM(C10:H10) -> 39150
A11: Dec-23 | B11: Q3 | C11: 20000 | D11: 8500 | E11: 5500 | F11: 4000 | G11: 1400 | H11: 1200 | I11: =SUM(C11:H11) -> 40600
A12: Jan-24 | B12: Q4 | C12: 20000 | D12: 8500 | E12: 4200 | F12: 3500 | G12: 1150 | H12: 980 | I12: =SUM(C12:H12) -> 38330
A13: Feb-24 | B13: Q4 | C13: 20000 | D13: 8500 | E13: 3800 | F13: 3300 | G13: 1100 | H13: 900 | I13: =SUM(C13:H13) -> 37600
A14: Mar-24 | B14: Q4 | C14: 20000 | D14: 8500 | E14: 3600 | F14: 3200 | G14: 1050 | H14: 850 | I14: =SUM(C14:H14) -> 37200

Sheet Analysis
A2: Total Revenue | B2: =SUM(Table2[Total_Revenue_SAR]) -> 392054
A3: Total Cost | B3: =SUM(Table2[Cost_SAR]) -> 240538.15
A4: Total Profit | B4: =SUM(Table2[Profit_SAR]) -> 151515.85 | G4: Month | H4: Revenue | J4: MOTH | K4: Revenue(SAR) | L4: MoM_Growth%
A5: Over all Margine% | B5: =Analysis!B4/Analysis!B2 -> 0.38646679 | G5: {=_xlfn.UNIQUE(Table2[Month])} -> Apr-23 | H5: =SUMIF(Table2[Month],G5,Table2[Total_Revenue_SAR]) -> 25297 | J5: Apr-23 | K5: =SUMIF(Table2[Month],Analysis!J5,Table2[Total_Revenue_SAR]) -> 25297 | L5: -
G6: May-23 | H6: =SUMIF(Table2[Month],G6,Table2[Total_Revenue_SAR]) -> 44687 | J6: May-23 | K6: =SUMIF(Table2[Month],Analysis!J6,Table2[Total_Revenue_SAR]) -> 44687 | L6: =(K6-K5)/K5 -> 0.76649405
G7: Jun-23 | H7: =SUMIF(Table2[Month],G7,Table2[Total_Revenue_SAR]) -> 30355 | J7: Jun-23 | K7: =SUMIF(Table2[Month],Analysis!J7,Table2[Total_Revenue_SAR]) -> 30355 | L7: =(K7-K6)/K6 -> -0.32071967
A8: Region | B8: Total_Revenue | D8: Order_ID | E8: Total_Revenue_SAR | G8: Jul-23 | H8: =SUMIF(Table2[Month],G8,Table2[Total_Revenue_SAR]) -> 44000 | J8: Jul-23 | K8: =SUMIF(Table2[Month],Analysis!J8,Table2[Total_Revenue_SAR]) -> 44000 | L8: =(K8-K7)/K7 -> 0.44951408
A9: Mecca | B9: =SUMIF(Table2[Region],Analysis!A9,Table2[Total_Revenue_SAR]) -> 92377 | D9: ORD-1024 | E9: =_xlfn.XLOOKUP(D9,Table2[Order_ID],Table2[Total_Revenue_SAR]) -> 247 | G9: Aug-23 | H9: =SUMIF(Table2[Month],G9,Table2[Total_Revenue_SAR]) -> 47881 | J9: Aug-23 | K9: =SUMIF(Table2[Month],Analysis!J9,Table2[Total_Revenue_SAR]) -> 47881 | L9: =(K9-K8)/K8 -> 0.088204545
A10: Medina | B10: =SUMIF(Table2[Region],Analysis!A10,Table2[Total_Revenue_SAR]) -> 85601 | D10: ORD-1033 | E10: =_xlfn.XLOOKUP(D10,Table2[Order_ID],Table2[Total_Revenue_SAR]) -> 110 | G10: Sep-23 | H10: =SUMIF(Table2[Month],G10,Table2[Total_Revenue_SAR]) -> 20680 | J10: Sep-23 | K10: =SUMIF(Table2[Month],Analysis!J10,Table2[Total_Revenue_SAR]) -> 20680 | L10: =(K10-K9)/K9 -> -0.5680959
A11: Jeddah | B11: =SUMIF(Table2[Region],Analysis!A11,Table2[Total_Revenue_SAR]) -> 82724 | D11: ORD-1092 | E11: =_xlfn.XLOOKUP(D11,Table2[Order_ID],Table2[Total_Revenue_SAR]) -> 266 | G11: Oct-23 | H11: =SUMIF(Table2[Month],G11,Table2[Total_Revenue_SAR]) -> 17292 | J11: Oct-23 | K11: =SUMIF(Table2[Month],Analysis!J11,Table2[Total_Revenue_SAR]) -> 17292 | L11: =(K11-K10)/K10 -> -0.16382979
A12: Dammam | B12: =SUMIF(Table2[Region],Analysis!A12,Table2[Total_Revenue_SAR]) -> 66021 | D12: ORD-1111 | E12: =_xlfn.XLOOKUP(D12,Table2[Order_ID],Table2[Total_Revenue_SAR]) -> 532 | G12: Nov-23 | H12: =SUMIF(Table2[Month],G12,Table2[Total_Revenue_SAR]) -> 27951 | J12: Nov-23 | K12: =SUMIF(Table2[Month],Analysis!J12,Table2[Total_Revenue_SAR]) -> 27951 | L12: =(K12-K11)/K11 -> 0.61641221
A13: Riyadh | B13: =SUMIF(Table2[Region],Analysis!A13,Table2[Total_Revenue_SAR]) -> 65331 | D13: ORD-1136 | E13: =_xlfn.XLOOKUP(D13,Table2[Order_ID],Table2[Total_Revenue_SAR]) -> 912 | G13: Dec-23 | H13: =SUMIF(Table2[Month],G13,Table2[Total_Revenue_SAR]) -> 52201 | J13: Dec-23 | K13: =SUMIF(Table2[Month],Analysis!J13,Table2[Total_Revenue_SAR]) -> 52201 | L13: =(K13-K12)/K12 -> 0.86758971
D14: ORD-1166 | E14: =_xlfn.XLOOKUP(D14,Table2[Order_ID],Table2[Total_Revenue_SAR]) -> 280 | G14: Jan-24 | H14: =SUMIF(Table2[Month],G14,Table2[Total_Revenue_SAR]) -> 33123 | J14: Jan-24 | K14: =SUMIF(Table2[Month],Analysis!J14,Table2[Total_Revenue_SAR]) -> 33123 | L14: =(K14-K13)/K13 -> -0.36547193
A15: Category | B15: Total_Revenue | D15: ORD-1172 | E15: =_xlfn.XLOOKUP(D15,Table2[Order_ID],Table2[Total_Revenue_SAR]) -> 28 | G15: Feb-24 | H15: =SUMIF(Table2[Month],G15,Table2[Total_Revenue_SAR]) -> 27714 | J15: Feb-24 | K15: =SUMIF(Table2[Month],Analysis!J15,Table2[Total_Revenue_SAR]) -> 27714 | L15: =(K15-K14)/K14 -> -0.16330043
A16: Electronics | B16: =SUMIF(Table2[Product_Category],Analysis!A16,Table2[Total_Revenue_SAR]) -> 108190 | G16: Mar-24 | H16: =SUMIF(Table2[Month],G16,Table2[Total_Revenue_SAR]) -> 20873 | J16: Mar-24 | K16: =SUMIF(Table2[Month],Analysis!J16,Table2[Total_Revenue_SAR]) -> 20873 | L16: =(K16-K15)/K15 -> -0.24684275
A17: Furniture | B17: =SUMIF(Table2[Product_Category],Analysis!A17,Table2[Total_Revenue_SAR]) -> 155910
A18: IT Equipment | B18: =SUMIF(Table2[Product_Category],Analysis!A18,Table2[Total_Revenue_SAR]) -> 109940
A19: Office Supplies | B19: =SUMIF(Table2[Product_Category],Analysis!A19,Table2[Total_Revenue_SAR]) -> 7991 | D19: Sales Person | E19: Average order value(SAR) | F19: Total Revenue (SAR) | G19: Rank
A20: Stationery | B20: =SUMIF(Table2[Product_Category],Analysis!A20,Table2[Total_Revenue_SAR]) -> 10023 | D20: Ahmed Al-Ghamdi | E20: =AVERAGEIF(Table2[Salesperson],Analysis!D20,Table2[Total_Revenue_SAR]) -> 2495.2759 | F20: =SUMIF(Table2[Salesperson],Analysis!D20,Table2[Total_Revenue_SAR]) -> 72363 | G20: =RANK(F20,$F$20:$F$26,0) -> 1
D21: Nora Bakr | E21: =AVERAGEIF(Table2[Salesperson],Analysis!D21,Table2[Total_Revenue_SAR]) -> 2814.76 | F21: =SUMIF(Table2[Salesperson],Analysis!D21,Table2[Total_Revenue_SAR]) -> 70369 | G21: =RANK(F21,$F$20:$F$26,0) -> 2
A22: Quarter | B22: order (Count) | D22: Fatima Hassan | E22: =AVERAGEIF(Table2[Salesperson],Analysis!D22,Table2[Total_Revenue_SAR]) -> 2182.4643 | F22: =SUMIF(Table2[Salesperson],Analysis!D22,Table2[Total_Revenue_SAR]) -> 61109 | G22: =RANK(F22,$F$20:$F$26,0) -> 3
A23: Q1 | B23: =COUNTIF(Table2[Quarter],Analysis!A23) -> 41 | D23: Omar Siddiqui | E23: =AVERAGEIF(Table2[Salesperson],Analysis!D23,Table2[Total_Revenue_SAR]) -> 2708.8182 | F23: =SUMIF(Table2[Salesperson],Analysis!D23,Table2[Total_Revenue_SAR]) -> 59594 | G23: =RANK(F23,$F$20:$F$26,0) -> 4
A24: Q2 | B24: =COUNTIF(Table2[Quarter],Analysis!A24) -> 48 | D24: Riyan K | E24: =AVERAGEIF(Table2[Salesperson],Analysis!D24,Table2[Total_Revenue_SAR]) -> 2502.8261 | F24: =SUMIF(Table2[Salesperson],Analysis!D24,Table2[Total_Revenue_SAR]) -> 57565 | G24: =RANK(F24,$F$20:$F$26,0) -> 5
A25: Q3 | B25: =COUNTIF(Table2[Quarter],Analysis!A25) -> 49 | D25: Sara Al-Otaibi | E25: =AVERAGEIF(Table2[Salesperson],Analysis!D25,Table2[Total_Revenue_SAR]) -> 1889.5714 | F25: =SUMIF(Table2[Salesperson],Analysis!D25,Table2[Total_Revenue_SAR]) -> 39681 | G25: =RANK(F25,$F$20:$F$26,0) -> 6
A26: Q4 | B26: =COUNTIF(Table2[Quarter],Analysis!A26) -> 34 | D26: Khalid Nasser | E26: =AVERAGEIF(Table2[Salesperson],Analysis!D26,Table2[Total_Revenue_SAR]) -> 1307.2083 | F26: =SUMIF(Table2[Salesperson],Analysis!D26,Table2[Total_Revenue_SAR]) -> 31373 | G26: =RANK(F26,$F$20:$F$26,0) -> 7

Sheet Pivot_Analysis
A3: Monthly Revenue Trend | D3: Profit by Region & Quarter | E3: Quarter
A4: Month | B4: Total | D4: Region | E4: Q1 | F4: Q2 | G4: Q3 | H4: Q4 | I4: Grand Total
A5: Apr-23 | B5: 25297 | D5: Dammam | E5: 4670.25 | F5: 6381.1 | G5: 5982.95 | H5: 8424.35 | I5: 25458.65
A6: May-23 | B6: 44687 | D6: Jeddah | E6: 6274.95 | F6: 2770.35 | G6: 4764.9 | H6: 17571.9 | I6: 31382.1
A7: Jun-23 | B7: 30355 | D7: Mecca | E7: 6121.85 | F7: 14476.45 | G7: 13165.35 | H7: 3017.85 | I7: 36781.5
A8: Jul-23 | B8: 44000 | D8: Medina | E8: 13917.35 | F8: 9761.05 | G8: 7350.9 | H8: 2184.4 | I8: 33213.7
A9: Aug-23 | B9: 47881 | D9: Riyadh | E9: 11962 | F9: 4976.5 | G9: 841.4 | H9: 6900 | I9: 24679.9
A10: Sep-23 | B10: 20680 | D10: Grand Total | E10: 42946.4 | F10: 38365.45 | G10: 32105.5 | H10: 38098.5 | I10: 151515.85
A11: Oct-23 | B11: 17292
A12: Nov-23 | B12: 27951
A13: Dec-23 | B13: 52201 | E13: Salesperson Performance Summary
A14: Jan-24 | B14: 33123 | D14: Salesperson | E14: Sum of Cost_SAR | F14: Sum of Total_Revenue_SAR | G14: Average of profit_Margine%
A15: Feb-24 | B15: 27714 | D15: Ahmed Al-Ghamdi | E15: 44957.8 | F15: 72363 | G15: 0.4162069
A16: Mar-24 | B16: 20873 | D16: Fatima Hassan | E16: 37448.1 | F16: 61109 | G16: 0.43285714
A17: Grand Total | B17: 392054 | D17: Khalid Nasser | E17: 18719.15 | F17: 31373 | G17: 0.46875
D18: Nora Bakr | E18: 43628.9 | F18: 70369 | G18: 0.4132
D19: Omar Siddiqui | E19: 36186.55 | F19: 59594 | G19: 0.42363636
A20: Top 5 Products by Units Sold | D20: Riyan K | E20: 34834.1 | F20: 57565 | G20: 0.42565217
A21: Product_Name | B21: Total | D21: Sara Al-Otaibi | E21: 24763.55 | F21: 39681 | G21: 0.44714286
A22: Webcam | B22: 141 | D22: Grand Total | E22: 240538.15 | F22: 392054 | G22: 0.43180233
A23: Whiteboard | B23: 136
A24: Logitech Keyboard | B24: 135
A25: Correction Tape | B25: 124
A26: Wi-Fi Router | B26: 122
A27: Grand Total | B27: 658

Sheet Sheet5
B3: Moth by Target and Actual SAR | E3: Revenue by Region | H3: %revenue by category
A4: Month | B4: Target_SAR | C4: Actual_SAR | E4: Region | F4: Total | H4: Product_Category | I4: Total
A5: Apr-23 | B5: 42000 | C5: 38500 | E5: Mecca | F5: 92377 | H5: Electronics | I5: 0.27595688
A6: May-23 | B6: 45000 | C6: 46200 | E6: Medina | F6: 85601 | H6: Furniture | I6: 0.39767481
A7: Jun-23 | B7: 48000 | C7: 51000 | E7: Jeddah | F7: 82724 | H7: IT Equipment | I7: 0.28042055
A8: Jul-23 | B8: 50000 | C8: 48800 | E8: Dammam | F8: 66021 | H8: Office Supplies | I8: 0.020382396
A9: Sep-23 | B9: 55000 | C9: 58900 | E9: Riyadh | F9: 65331 | H9: Stationery | I9: 0.025565356
A10: Aug-23 | B10: 52000 | C10: 53400 | E10: Grand Total | F10: 392054 | H10: Grand Total | I10: 1
A11: Oct-23 | B11: 57000 | C11: 55000
A12: Nov-23 | B12: 60000 | C12: 63200
A13: Dec-23 | B13: 65000 | C13: 70100 | E13: Profit_by_Quarter | H13: Top5 salesperson
A14: Jan-24 | B14: 58000 | C14: 54300 | E14: Quarter | F14: Total | H14: Salesperson | I14: Total
A15: Feb-24 | B15: 56000 | C15: 57800 | E15: Q1 | F15: 38098.5 | H15: Ahmed Al-Ghamdi | I15: 72363
A16: Mar-24 | B16: 54000 | C16: 52600 | E16: Q2 | F16: 42946.4 | H16: Nora Bakr | I16: 70369
A17: Grand Total | B17: 642000 | C17: 649800 | E17: Q3 | F17: 38365.45 | H17: Fatima Hassan | I17: 61109
E18: Q4 | F18: 32105.5 | H18: Omar Siddiqui | I18: 59594
E19: Grand Total | F19: 151515.85 | H19: Riyan K | I19: 57565
H20: Grand Total | I20: 321000

Sheet DASHBOARD
